{
  "epics": [
    {
      "name": "",
      "users": [],
      "sequential_order": 1,
      "estimated_stories": null,
      "sub_epics": [
        {
          "name": "",
          "users": [],
          "sequential_order": 1,
          "features": [
            {
              "name": "",
              "users": [],
              "sequential_order": 1,
              "estimated_stories": null,
              "stories": [
                {
                  "name": "",
                  "users": [],
                  "sequential_order": 1
                }
              ]
            }
          ]
        }
      ],
      "features": [
        {
          "name": "",
          "users": [],
          "sequential_order": 1,
          "stories": [
            {
              "name": "",
              "users": [],
              "sequential_order": 1
            }
          ]
        }
      ]
    }
  ],
  "increments": [
    {
      "name": "",
      "priority": 1,
      "epics": [
        {
          "name": "",
          "users": [],
          "sequential_order": 1,
          "estimated_stories": null,
          "features": [
            {
              "name": "",
              "users": [],
              "sequential_order": 1,
              "estimated_stories": null,
              "stories": [
                {
                  "name": "",
                  "users": [],
                  "sequential_order": 1
                }
              ]
            }
          ]
        }
      ]
    },
    {
      "name": "",
      "priority": 2,
      "epics": [
        {
          "name": "",
          "users": [],
          "sequential_order": 1,
          "estimated_stories": null,
          "features": [
            {
              "name": "",
              "users": [],
              "sequential_order": 1,
              "estimated_stories": null,
              "stories": [
                {
                  "name": "",
                  "users": [],
                  "sequential_order": 1
                }
              ]
            }
          ]
        }
      ]
    },
    {
      "name": "",
      "priority": 3,
      "epics": [
        {
          "name": "",
          "users": [],
          "sequential_order": 1,
          "estimated_stories": null,
          "features": [
            {
              "name": "",
              "users": [],
              "sequential_order": 1,
              "estimated_stories": null,
              "stories": [
                {
                  "name": "",
                  "users": [],
                  "sequential_order": 1
                }
              ]
            }
          ]
        }
      ]
    }
  ]
}

